odoo/addons/hr_holidays_public_overtime/README.rst
odoo/addons/hr_holidays_public_overtime/__init__.py
odoo/addons/hr_holidays_public_overtime/__manifest__.py
odoo/addons/hr_holidays_public_overtime/i18n/de.po
odoo/addons/hr_holidays_public_overtime/i18n/hr_holidays_public_overtime.pot
odoo/addons/hr_holidays_public_overtime/i18n/it.po
odoo/addons/hr_holidays_public_overtime/models/__init__.py
odoo/addons/hr_holidays_public_overtime/models/hr_attendance.py
odoo/addons/hr_holidays_public_overtime/readme/CONTRIBUTORS.rst
odoo/addons/hr_holidays_public_overtime/readme/DESCRIPTION.rst
odoo/addons/hr_holidays_public_overtime/readme/USAGE.rst
odoo/addons/hr_holidays_public_overtime/static/description/icon.png
odoo/addons/hr_holidays_public_overtime/static/description/index.html
odoo/addons/hr_holidays_public_overtime/tests/__init__.py
odoo/addons/hr_holidays_public_overtime/tests/test_hr_holidays_public_attendance.py
odoo_addon_hr_holidays_public_overtime-15.0.1.0.1.4.dist-info/METADATA
odoo_addon_hr_holidays_public_overtime-15.0.1.0.1.4.dist-info/WHEEL
odoo_addon_hr_holidays_public_overtime-15.0.1.0.1.4.dist-info/top_level.txt
odoo_addon_hr_holidays_public_overtime-15.0.1.0.1.4.dist-info/RECORD
