Metadata-Version: 2.1
Name: odoo-addon-hr-holidays-public-overtime
Version: 15.0.1.0.1.4
Summary: Support public holidays in overtime calculations
Home-page: https://github.com/OCA/hr-holidays
Author: Hunki Enterprises BV, Odoo Community Association (OCA), verdigado eG
Author-email: support@odoo-community.org
License: AGPL-3
Platform: UNKNOWN
Classifier: Programming Language :: Python
Classifier: Framework :: Odoo
Classifier: Framework :: Odoo :: 15.0
Classifier: License :: OSI Approved :: GNU Affero General Public License v3
Classifier: Development Status :: 4 - Beta
Requires-Python: >=3.8
Requires-Dist: odoo-addon-hr-holidays-public <15.1dev,>=15.0dev
Requires-Dist: odoo <15.1dev,>=15.0a
